windows_atom/__init__.py
windows_atom/windows_atom.py
windows_atom-1.4.dist-info/LICENSE
windows_atom-1.4.dist-info/METADATA
windows_atom-1.4.dist-info/WHEEL
windows_atom-1.4.dist-info/top_level.txt
windows_atom-1.4.dist-info/RECORD
