Metadata-Version: 2.1
Name: windows-atom
Version: 1.4
Summary: A Python library to interact with the Windows atom table via ctypes.
Home-page: https://github.com/Mohamed-Adil-Cyber/windows_atom
Author: Mohamed Adil
Author-email: Mohamed Adil <MohamedAdilOfficial@gmail.com>
License: MIT
Project-URL: Homepage, https://github.com/Mohamed-Adil-Cyber/windows_atom
Classifier: Programming Language :: Python :: 3
Classifier: License :: OSI Approved :: MIT License
Classifier: Operating System :: Microsoft :: Windows
Requires-Python: >=3.6
License-File: LICENSE
